MAOC_mol_rep/__init__.py
MAOC_mol_rep/maoc.py
maoc_mol_rep-0.0.4.dist-info/METADATA
maoc_mol_rep-0.0.4.dist-info/WHEEL
maoc_mol_rep-0.0.4.dist-info/licenses/LICENSE
maoc_mol_rep-0.0.4.dist-info/RECORD
