Metadata-Version: 2.1
Name: MAOC_mol_rep
Version: 0.0.4
Summary: The code for generating the MAOC representation, the PCX MAOC, optimising the hyperparameters sigma and lambda, and carrying out regression tasks using the KRR model are all included in this package.
Project-URL: Homepage, https://github.com/HITS-CCC
Author-email: Stiv Llenga <stiv.llenga@h-its.org>, Ganna Gryn'ova <ganna.grynova@h-its.org>
Maintainer-email: Stiv Llenga <stiv.llenga@h-its.org>
License-File: LICENSE
Classifier: License :: OSI Approved :: MIT License
Classifier: Operating System :: OS Independent
Classifier: Programming Language :: Python :: 3
Requires-Python: >=3.7
